posnoise/__init__.py
posnoise/core.py
posnoise/pattern_list/POSNoise_PatternList_Ver.2.1.txt
posnoise-0.0.1.dist-info/METADATA
posnoise-0.0.1.dist-info/WHEEL
posnoise-0.0.1.dist-info/licenses/LICENSE
posnoise-0.0.1.dist-info/RECORD
